{"inkVersion":21,"root":[["^Ohhh this is a fun one! The <color=red>Laser Gun</color>!","#","^speaker:Big Joe ","/#","#","^portrait:bigjoeneut ","/#","#","^layout:right ","/#","#","^audio:animal_crossing_high","/#","\n","^Press <color=blue>Left Mouse</color> to fire the <color=red>Laser Gun</color>!","#","^speaker:Big Joe ","/#","#","^portrait:bigjoedetermined ","/#","#","^layout:right ","/#","#","^audio:animal_crossing_high","/#","\n","^Note that the firing direction is based on where you click on the screen.","#","^speaker:Big Joe ","/#","#","^portrait:bigjoeneut ","/#","#","^layout:right ","/#","#","^audio:animal_crossing_mid","/#","\n","^Don't make me look dumb player... ","#","^portrait:bigjoedetermined","/#","\n","end",["done",{"#f":5,"#n":"g-0"}],null],"done",{"#f":1}],"listDefs":{}}